curve_matcher-0.2.0.dist-info/METADATA
curve_matcher-0.2.0.dist-info/WHEEL
curve_matcher-0.2.0.dist-info/licenses/LICENSE
curve_matcher/__init__.py
curve_matcher/frechet_distance.py
curve_matcher/geometry.py
curve_matcher/procrustes_analysis.py
curve_matcher/py.typed
curve_matcher/shape_similarity.py
curve_matcher-0.2.0.dist-info/RECORD
