Metadata-Version: 2.1
Name: curve-matcher
Version: 0.2.0
Summary: A Python library for doing curve matching with Fréchet distance and Procrustes analysis
Author-Email: David Chanin <chanindav@gmail.com>
License: MIT
Requires-Python: >=3.10
